{
  "metadata": {
    "title": "Moss: Biology, Ecology, Design, and Sustainability",
    "description": "A comprehensive learning graph for the Moss intelligent textbook covering 400 concepts across moss biology, ecology, garden design, indoor systems, architecture, art, practical skills, education, advanced topics, and future applications.",
    "creator": "Dan McCreary",
    "date": "2026-03-20",
    "version": "1.0",
    "format": "Learning Graph JSON v1.0",
    "schema": "https://raw.githubusercontent.com/dmccreary/learning-graphs/refs/heads/main/src/schema/learning-graph-schema.json",
    "license": "CC BY-NC-SA 4.0 DEED"
  },
  "groups": {
    "FOUND": {
      "classifierName": "Foundation Concepts",
      "color": "MistyRose",
      "font": {
        "color": "black"
      }
    },
    "TYPES": {
      "classifierName": "Moss Types & Identification",
      "color": "PeachPuff",
      "font": {
        "color": "black"
      }
    },
    "ECOL": {
      "classifierName": "Ecology & Ecosystems",
      "color": "Honeydew",
      "font": {
        "color": "black"
      }
    },
    "WATER": {
      "classifierName": "Water & Climate",
      "color": "PaleTurquoise",
      "font": {
        "color": "black"
      }
    },
    "GARD": {
      "classifierName": "Garden Design",
      "color": "PaleGreen",
      "font": {
        "color": "black"
      }
    },
    "INDOOR": {
      "classifierName": "Indoor Moss Systems",
      "color": "LightYellow",
      "font": {
        "color": "black"
      }
    },
    "ARCH": {
      "classifierName": "Architecture & Sustainability",
      "color": "LightSteelBlue",
      "font": {
        "color": "black"
      }
    },
    "ART": {
      "classifierName": "Art, Culture & Expression",
      "color": "Lavender",
      "font": {
        "color": "black"
      }
    },
    "PRACT": {
      "classifierName": "Practical Skills & DIY",
      "color": "Thistle",
      "font": {
        "color": "black"
      }
    },
    "EDUC": {
      "classifierName": "Education & Life Stages",
      "color": "LightPink",
      "font": {
        "color": "black"
      }
    },
    "ADV": {
      "classifierName": "Advanced & Systems Topics",
      "color": "PowderBlue",
      "font": {
        "color": "black"
      }
    },
    "FUTURE": {
      "classifierName": "Future Applications",
      "color": "Plum",
      "font": {
        "color": "white"
      }
    },
    "XCUT": {
      "classifierName": "Cross-Cutting Skills & Science",
      "color": "Gainsboro",
      "font": {
        "color": "black"
      }
    }
  },
  "nodes": [
    {
      "id": 1,
      "label": "Moss Definition",
      "group": "FOUND",
      "shape": "box"
    },
    {
      "id": 2,
      "label": "Bryophytes",
      "group": "FOUND"
    },
    {
      "id": 3,
      "label": "Liverworts",
      "group": "FOUND"
    },
    {
      "id": 4,
      "label": "Hornworts",
      "group": "FOUND"
    },
    {
      "id": 5,
      "label": "Non-Vascular Plants",
      "group": "FOUND"
    },
    {
      "id": 6,
      "label": "Vascular Plants",
      "group": "FOUND",
      "shape": "box"
    },
    {
      "id": 7,
      "label": "Plant Evolution",
      "group": "FOUND",
      "shape": "box"
    },
    {
      "id": 8,
      "label": "Land Plant Origins",
      "group": "FOUND"
    },
    {
      "id": 9,
      "label": "Moss Diversity",
      "group": "FOUND"
    },
    {
      "id": 10,
      "label": "Moss Classification",
      "group": "FOUND"
    },
    {
      "id": 11,
      "label": "Moss vs Ferns",
      "group": "FOUND"
    },
    {
      "id": 12,
      "label": "Moss vs Grass",
      "group": "FOUND"
    },
    {
      "id": 13,
      "label": "Moss vs Succulents",
      "group": "FOUND"
    },
    {
      "id": 14,
      "label": "Moss vs Algae",
      "group": "FOUND"
    },
    {
      "id": 15,
      "label": "Vascular System",
      "group": "FOUND"
    },
    {
      "id": 16,
      "label": "Non-Vascular Transport",
      "group": "FOUND"
    },
    {
      "id": 17,
      "label": "Growth Rate Comparison",
      "group": "FOUND"
    },
    {
      "id": 18,
      "label": "Environmental Resilience",
      "group": "FOUND"
    },
    {
      "id": 19,
      "label": "Gametophyte",
      "group": "FOUND"
    },
    {
      "id": 20,
      "label": "Sporophyte",
      "group": "FOUND"
    },
    {
      "id": 21,
      "label": "Alternation of Generations",
      "group": "FOUND"
    },
    {
      "id": 22,
      "label": "Rhizoids",
      "group": "FOUND"
    },
    {
      "id": 23,
      "label": "Moss Leaves",
      "group": "FOUND"
    },
    {
      "id": 24,
      "label": "Moss Stems",
      "group": "FOUND"
    },
    {
      "id": 25,
      "label": "Spore Capsule",
      "group": "FOUND"
    },
    {
      "id": 26,
      "label": "Seta",
      "group": "FOUND"
    },
    {
      "id": 27,
      "label": "Calyptra",
      "group": "FOUND"
    },
    {
      "id": 28,
      "label": "Spores",
      "group": "FOUND"
    },
    {
      "id": 29,
      "label": "Spore Dispersal",
      "group": "FOUND"
    },
    {
      "id": 30,
      "label": "Spores vs Seeds",
      "group": "FOUND"
    },
    {
      "id": 31,
      "label": "Water in Fertilization",
      "group": "FOUND"
    },
    {
      "id": 32,
      "label": "Moss Life Cycle",
      "group": "FOUND"
    },
    {
      "id": 33,
      "label": "Protonema",
      "group": "FOUND"
    },
    {
      "id": 34,
      "label": "Moss Sexual Reproduction",
      "group": "FOUND"
    },
    {
      "id": 35,
      "label": "Asexual Reproduction",
      "group": "FOUND"
    },
    {
      "id": 36,
      "label": "Moss Cell Structure",
      "group": "FOUND"
    },
    {
      "id": 37,
      "label": "Chloroplasts in Moss",
      "group": "FOUND"
    },
    {
      "id": 38,
      "label": "Photosynthesis in Moss",
      "group": "FOUND"
    },
    {
      "id": 39,
      "label": "Sheet Moss",
      "group": "TYPES"
    },
    {
      "id": 40,
      "label": "Cushion Moss",
      "group": "TYPES"
    },
    {
      "id": 41,
      "label": "Haircap Moss",
      "group": "TYPES"
    },
    {
      "id": 42,
      "label": "Rock Cap Moss",
      "group": "TYPES"
    },
    {
      "id": 43,
      "label": "Sphagnum Moss",
      "group": "TYPES"
    },
    {
      "id": 44,
      "label": "Peat Moss",
      "group": "TYPES"
    },
    {
      "id": 45,
      "label": "Fern Moss",
      "group": "TYPES"
    },
    {
      "id": 46,
      "label": "Mood Moss",
      "group": "TYPES"
    },
    {
      "id": 47,
      "label": "Reindeer Moss",
      "group": "TYPES"
    },
    {
      "id": 48,
      "label": "Java Moss",
      "group": "TYPES"
    },
    {
      "id": 49,
      "label": "Star Moss",
      "group": "TYPES"
    },
    {
      "id": 50,
      "label": "Broom Moss",
      "group": "TYPES"
    },
    {
      "id": 51,
      "label": "Plume Moss",
      "group": "TYPES"
    },
    {
      "id": 52,
      "label": "Forest Moss",
      "group": "TYPES"
    },
    {
      "id": 53,
      "label": "Aquatic Moss",
      "group": "TYPES"
    },
    {
      "id": 54,
      "label": "Urban Moss",
      "group": "TYPES"
    },
    {
      "id": 55,
      "label": "Moss Habitat Types",
      "group": "TYPES"
    },
    {
      "id": 56,
      "label": "Acrocarpous Moss",
      "group": "TYPES"
    },
    {
      "id": 57,
      "label": "Pleurocarpous Moss",
      "group": "TYPES"
    },
    {
      "id": 58,
      "label": "Moss Growth Forms",
      "group": "TYPES"
    },
    {
      "id": 59,
      "label": "Moss Identification",
      "group": "TYPES"
    },
    {
      "id": 60,
      "label": "Moss Field Guides",
      "group": "TYPES"
    },
    {
      "id": 61,
      "label": "Dichotomous Key Basics",
      "group": "TYPES"
    },
    {
      "id": 62,
      "label": "Moss Photography",
      "group": "TYPES"
    },
    {
      "id": 63,
      "label": "Hand Lens Use",
      "group": "TYPES"
    },
    {
      "id": 64,
      "label": "Moss Color Variation",
      "group": "TYPES"
    },
    {
      "id": 65,
      "label": "Moss Texture",
      "group": "TYPES"
    },
    {
      "id": 66,
      "label": "Moss Ecology",
      "group": "ECOL"
    },
    {
      "id": 67,
      "label": "Ecosystem Services",
      "group": "ECOL",
      "shape": "box"
    },
    {
      "id": 68,
      "label": "Water Retention",
      "group": "WATER"
    },
    {
      "id": 69,
      "label": "Soil Formation",
      "group": "ECOL"
    },
    {
      "id": 70,
      "label": "Primary Succession",
      "group": "ECOL"
    },
    {
      "id": 71,
      "label": "Microhabitats",
      "group": "ECOL"
    },
    {
      "id": 72,
      "label": "Moss in Forests",
      "group": "ECOL"
    },
    {
      "id": 73,
      "label": "Moss in Tundra",
      "group": "ECOL"
    },
    {
      "id": 74,
      "label": "Moss in Wetlands",
      "group": "ECOL"
    },
    {
      "id": 75,
      "label": "Moss in Deserts",
      "group": "ECOL"
    },
    {
      "id": 76,
      "label": "Moss Biodiversity",
      "group": "ECOL"
    },
    {
      "id": 77,
      "label": "Capillary Action",
      "group": "WATER"
    },
    {
      "id": 78,
      "label": "Water Absorption Mechanics",
      "group": "WATER"
    },
    {
      "id": 79,
      "label": "Fog Harvesting",
      "group": "WATER"
    },
    {
      "id": 80,
      "label": "Rainfall Interception",
      "group": "WATER"
    },
    {
      "id": 81,
      "label": "Evapotranspiration",
      "group": "WATER"
    },
    {
      "id": 82,
      "label": "Hydrological Cycle",
      "group": "WATER"
    },
    {
      "id": 83,
      "label": "Moss Water Storage",
      "group": "WATER"
    },
    {
      "id": 84,
      "label": "Desiccation Tolerance",
      "group": "WATER"
    },
    {
      "id": 85,
      "label": "Rehydration Ability",
      "group": "WATER"
    },
    {
      "id": 86,
      "label": "Carbon Sequestration",
      "group": "WATER"
    },
    {
      "id": 87,
      "label": "Carbon Cycle",
      "group": "WATER",
      "shape": "box"
    },
    {
      "id": 88,
      "label": "Moss as Carbon Sink",
      "group": "WATER"
    },
    {
      "id": 89,
      "label": "Climate Change Effects",
      "group": "WATER"
    },
    {
      "id": 90,
      "label": "Moss Climate Indicators",
      "group": "WATER"
    },
    {
      "id": 91,
      "label": "Temperature Sensitivity",
      "group": "WATER"
    },
    {
      "id": 92,
      "label": "Pollution Sensitivity",
      "group": "WATER"
    },
    {
      "id": 93,
      "label": "Air Quality Monitoring",
      "group": "WATER"
    },
    {
      "id": 94,
      "label": "Bioindicator Species",
      "group": "ECOL"
    },
    {
      "id": 95,
      "label": "Heavy Metal Absorption",
      "group": "WATER"
    },
    {
      "id": 96,
      "label": "Moss and Acid Rain",
      "group": "WATER"
    },
    {
      "id": 97,
      "label": "Urban Ecology",
      "group": "ECOL"
    },
    {
      "id": 98,
      "label": "Ecological Monitoring",
      "group": "ECOL"
    },
    {
      "id": 99,
      "label": "Moss Microbiome",
      "group": "ECOL"
    },
    {
      "id": 100,
      "label": "Moss-Associated Bacteria",
      "group": "ECOL"
    },
    {
      "id": 101,
      "label": "Moss-Associated Fungi",
      "group": "ECOL"
    },
    {
      "id": 102,
      "label": "Nitrogen Fixation",
      "group": "ECOL"
    },
    {
      "id": 103,
      "label": "Symbiotic Systems",
      "group": "ECOL"
    },
    {
      "id": 104,
      "label": "Decomposition Role",
      "group": "ECOL"
    },
    {
      "id": 105,
      "label": "Nutrient Cycling",
      "group": "ECOL"
    },
    {
      "id": 106,
      "label": "Moss Food Webs",
      "group": "ECOL"
    },
    {
      "id": 107,
      "label": "Invertebrate Habitats",
      "group": "ECOL"
    },
    {
      "id": 108,
      "label": "Peat Bogs",
      "group": "ECOL"
    },
    {
      "id": 109,
      "label": "Peatland Ecology",
      "group": "ECOL"
    },
    {
      "id": 110,
      "label": "Sphagnum Water Holding",
      "group": "ECOL"
    },
    {
      "id": 111,
      "label": "Wetland Conservation",
      "group": "ECOL"
    },
    {
      "id": 112,
      "label": "Moss Garden Benefits",
      "group": "GARD"
    },
    {
      "id": 113,
      "label": "Low Maintenance Gardens",
      "group": "GARD"
    },
    {
      "id": 114,
      "label": "No Mowing Required",
      "group": "GARD"
    },
    {
      "id": 115,
      "label": "Shade Tolerance",
      "group": "GARD"
    },
    {
      "id": 116,
      "label": "Moss Aesthetic Qualities",
      "group": "GARD"
    },
    {
      "id": 117,
      "label": "Site Assessment",
      "group": "GARD"
    },
    {
      "id": 118,
      "label": "Light Conditions",
      "group": "GARD"
    },
    {
      "id": 119,
      "label": "Moisture Levels",
      "group": "GARD"
    },
    {
      "id": 120,
      "label": "Soil Acidity",
      "group": "GARD"
    },
    {
      "id": 121,
      "label": "Soil pH Testing",
      "group": "GARD"
    },
    {
      "id": 122,
      "label": "Climate Zones",
      "group": "GARD",
      "shape": "box"
    },
    {
      "id": 123,
      "label": "Hardiness Zones",
      "group": "GARD"
    },
    {
      "id": 124,
      "label": "Species Selection",
      "group": "GARD"
    },
    {
      "id": 125,
      "label": "Moss Garden Site Prep",
      "group": "GARD"
    },
    {
      "id": 126,
      "label": "Removing Existing Grass",
      "group": "GARD"
    },
    {
      "id": 127,
      "label": "Soil Compaction",
      "group": "GARD"
    },
    {
      "id": 128,
      "label": "Transplanting Moss",
      "group": "GARD"
    },
    {
      "id": 129,
      "label": "Encouraging Growth",
      "group": "GARD"
    },
    {
      "id": 130,
      "label": "Watering Techniques",
      "group": "GARD"
    },
    {
      "id": 131,
      "label": "Japanese Moss Gardens",
      "group": "GARD"
    },
    {
      "id": 132,
      "label": "Woodland Garden Style",
      "group": "GARD"
    },
    {
      "id": 133,
      "label": "Minimalist Zen Layouts",
      "group": "GARD"
    },
    {
      "id": 134,
      "label": "Moss Pathways",
      "group": "GARD"
    },
    {
      "id": 135,
      "label": "Moss and Stone Design",
      "group": "GARD"
    },
    {
      "id": 136,
      "label": "Moss Ground Cover",
      "group": "GARD"
    },
    {
      "id": 137,
      "label": "Companion Plants",
      "group": "GARD"
    },
    {
      "id": 138,
      "label": "Shade Garden Design",
      "group": "GARD"
    },
    {
      "id": 139,
      "label": "Rain Garden Integration",
      "group": "GARD"
    },
    {
      "id": 140,
      "label": "Moss Lawn Alternative",
      "group": "GARD"
    },
    {
      "id": 141,
      "label": "Turf Grass Comparison",
      "group": "GARD"
    },
    {
      "id": 142,
      "label": "Cost Comparison",
      "group": "GARD"
    },
    {
      "id": 143,
      "label": "Water Use Comparison",
      "group": "GARD"
    },
    {
      "id": 144,
      "label": "Chemical Input Reduction",
      "group": "GARD"
    },
    {
      "id": 145,
      "label": "Carbon Footprint Analysis",
      "group": "GARD"
    },
    {
      "id": 146,
      "label": "Maintenance Calendar",
      "group": "GARD"
    },
    {
      "id": 147,
      "label": "Seasonal Moss Care",
      "group": "GARD"
    },
    {
      "id": 148,
      "label": "Winter Dormancy",
      "group": "GARD"
    },
    {
      "id": 149,
      "label": "Spring Recovery",
      "group": "GARD"
    },
    {
      "id": 150,
      "label": "Mossarium Definition",
      "group": "INDOOR"
    },
    {
      "id": 151,
      "label": "Open Mossariums",
      "group": "INDOOR"
    },
    {
      "id": 152,
      "label": "Closed Mossariums",
      "group": "INDOOR"
    },
    {
      "id": 153,
      "label": "Mossarium Materials",
      "group": "INDOOR"
    },
    {
      "id": 154,
      "label": "Glass Container Selection",
      "group": "INDOOR"
    },
    {
      "id": 155,
      "label": "Substrate Layers",
      "group": "INDOOR"
    },
    {
      "id": 156,
      "label": "Drainage Layer",
      "group": "INDOOR"
    },
    {
      "id": 157,
      "label": "Activated Charcoal Layer",
      "group": "INDOOR"
    },
    {
      "id": 158,
      "label": "Mossarium Soil Mix",
      "group": "INDOOR"
    },
    {
      "id": 159,
      "label": "Mossarium Assembly",
      "group": "INDOOR"
    },
    {
      "id": 160,
      "label": "Humidity Balance",
      "group": "INDOOR"
    },
    {
      "id": 161,
      "label": "Condensation Management",
      "group": "INDOOR"
    },
    {
      "id": 162,
      "label": "Mossarium Lighting",
      "group": "INDOOR"
    },
    {
      "id": 163,
      "label": "LED Grow Lights",
      "group": "INDOOR"
    },
    {
      "id": 164,
      "label": "Natural Light Needs",
      "group": "INDOOR"
    },
    {
      "id": 165,
      "label": "Mossarium Maintenance",
      "group": "INDOOR"
    },
    {
      "id": 166,
      "label": "Misting Techniques",
      "group": "INDOOR"
    },
    {
      "id": 167,
      "label": "Pruning Moss",
      "group": "INDOOR"
    },
    {
      "id": 168,
      "label": "Mold Prevention",
      "group": "INDOOR"
    },
    {
      "id": 169,
      "label": "Pest Management",
      "group": "INDOOR"
    },
    {
      "id": 170,
      "label": "Moss Tabletop Designs",
      "group": "INDOOR"
    },
    {
      "id": 171,
      "label": "Glass Installations",
      "group": "INDOOR"
    },
    {
      "id": 172,
      "label": "Miniature Landscapes",
      "group": "INDOOR"
    },
    {
      "id": 173,
      "label": "Living Moss Walls",
      "group": "INDOOR"
    },
    {
      "id": 174,
      "label": "Preserved Moss",
      "group": "INDOOR"
    },
    {
      "id": 175,
      "label": "Living vs Preserved Moss",
      "group": "INDOOR"
    },
    {
      "id": 176,
      "label": "Moss Wall Irrigation",
      "group": "INDOOR"
    },
    {
      "id": 177,
      "label": "Structural Requirements",
      "group": "INDOOR"
    },
    {
      "id": 178,
      "label": "Vertical Garden Systems",
      "group": "INDOOR"
    },
    {
      "id": 179,
      "label": "Biophilic Design",
      "group": "INDOOR"
    },
    {
      "id": 180,
      "label": "Stress Reduction Benefits",
      "group": "INDOOR"
    },
    {
      "id": 181,
      "label": "Indoor Air Quality",
      "group": "INDOOR"
    },
    {
      "id": 182,
      "label": "Psychological Benefits",
      "group": "INDOOR"
    },
    {
      "id": 183,
      "label": "Nature Connection Indoors",
      "group": "INDOOR"
    },
    {
      "id": 184,
      "label": "Office Moss Installations",
      "group": "INDOOR"
    },
    {
      "id": 185,
      "label": "Green Roofs",
      "group": "ARCH"
    },
    {
      "id": 186,
      "label": "Green Roof Types",
      "group": "ARCH"
    },
    {
      "id": 187,
      "label": "Extensive Green Roofs",
      "group": "ARCH"
    },
    {
      "id": 188,
      "label": "Intensive Green Roofs",
      "group": "ARCH"
    },
    {
      "id": 189,
      "label": "Moss Roof Benefits",
      "group": "ARCH"
    },
    {
      "id": 190,
      "label": "Roof Structural Load",
      "group": "ARCH"
    },
    {
      "id": 191,
      "label": "Roof Waterproofing",
      "group": "ARCH"
    },
    {
      "id": 192,
      "label": "Passive Cooling",
      "group": "ARCH"
    },
    {
      "id": 193,
      "label": "Moisture Buffering",
      "group": "ARCH"
    },
    {
      "id": 194,
      "label": "Sound Absorption",
      "group": "ARCH"
    },
    {
      "id": 195,
      "label": "Thermal Insulation",
      "group": "ARCH"
    },
    {
      "id": 196,
      "label": "Stormwater Management",
      "group": "ARCH"
    },
    {
      "id": 197,
      "label": "Runoff Reduction",
      "group": "ARCH"
    },
    {
      "id": 198,
      "label": "Heat Island Effect",
      "group": "ARCH"
    },
    {
      "id": 199,
      "label": "Heat Island Mitigation",
      "group": "ARCH"
    },
    {
      "id": 200,
      "label": "Urban Green Spaces",
      "group": "ARCH"
    },
    {
      "id": 201,
      "label": "Moss in Commercial Buildings",
      "group": "ARCH"
    },
    {
      "id": 202,
      "label": "Office Branding Nature",
      "group": "ARCH"
    },
    {
      "id": 203,
      "label": "Maintenance Economics",
      "group": "ARCH"
    },
    {
      "id": 204,
      "label": "Sustainable Architecture",
      "group": "ARCH"
    },
    {
      "id": 205,
      "label": "LEED Certification",
      "group": "ARCH"
    },
    {
      "id": 206,
      "label": "Living Building Challenge",
      "group": "ARCH"
    },
    {
      "id": 207,
      "label": "Climate-Resilient Cities",
      "group": "ARCH"
    },
    {
      "id": 208,
      "label": "Urban Biodiversity",
      "group": "ARCH"
    },
    {
      "id": 209,
      "label": "Permeable Surfaces",
      "group": "ARCH"
    },
    {
      "id": 210,
      "label": "Green Infrastructure",
      "group": "ARCH"
    },
    {
      "id": 211,
      "label": "Sustainable Homes",
      "group": "ARCH"
    },
    {
      "id": 212,
      "label": "Energy Efficiency",
      "group": "ARCH"
    },
    {
      "id": 213,
      "label": "Building Envelope",
      "group": "ARCH",
      "shape": "box"
    },
    {
      "id": 214,
      "label": "Moss Art Overview",
      "group": "ART"
    },
    {
      "id": 215,
      "label": "Framed Moss Art",
      "group": "ART"
    },
    {
      "id": 216,
      "label": "Moss Paintings",
      "group": "ART"
    },
    {
      "id": 217,
      "label": "Moss Graffiti",
      "group": "ART"
    },
    {
      "id": 218,
      "label": "Living Sculptures",
      "group": "ART"
    },
    {
      "id": 219,
      "label": "Sculpture Armatures",
      "group": "ART"
    },
    {
      "id": 220,
      "label": "Moss Substrates for Art",
      "group": "ART"
    },
    {
      "id": 221,
      "label": "Moss Color in Design",
      "group": "ART"
    },
    {
      "id": 222,
      "label": "Texture in Moss Art",
      "group": "ART"
    },
    {
      "id": 223,
      "label": "Moss Photography Art",
      "group": "ART"
    },
    {
      "id": 224,
      "label": "Japanese Garden Design",
      "group": "ART"
    },
    {
      "id": 225,
      "label": "Wabi-Sabi Philosophy",
      "group": "ART"
    },
    {
      "id": 226,
      "label": "Zen Garden Principles",
      "group": "ART"
    },
    {
      "id": 227,
      "label": "Moss in Ikebana",
      "group": "ART"
    },
    {
      "id": 228,
      "label": "Historical Moss Uses",
      "group": "ART"
    },
    {
      "id": 229,
      "label": "Celtic Moss Traditions",
      "group": "ART"
    },
    {
      "id": 230,
      "label": "Moss in Literature",
      "group": "ART"
    },
    {
      "id": 231,
      "label": "Moss in Folklore",
      "group": "ART"
    },
    {
      "id": 232,
      "label": "Contemplative Gardens",
      "group": "ART"
    },
    {
      "id": 233,
      "label": "Sacred Groves",
      "group": "ART"
    },
    {
      "id": 234,
      "label": "Healing Gardens",
      "group": "ART"
    },
    {
      "id": 235,
      "label": "Sensory Garden Design",
      "group": "ART"
    },
    {
      "id": 236,
      "label": "Ethical Harvesting",
      "group": "PRACT"
    },
    {
      "id": 237,
      "label": "Wild Harvesting Concerns",
      "group": "PRACT"
    },
    {
      "id": 238,
      "label": "Harvesting Permits",
      "group": "PRACT"
    },
    {
      "id": 239,
      "label": "Sustainable Collection",
      "group": "PRACT"
    },
    {
      "id": 240,
      "label": "Moss Propagation",
      "group": "PRACT"
    },
    {
      "id": 241,
      "label": "Fragmentation Method",
      "group": "PRACT"
    },
    {
      "id": 242,
      "label": "Moss Slurry Method",
      "group": "PRACT"
    },
    {
      "id": 243,
      "label": "Slurry Myths",
      "group": "PRACT"
    },
    {
      "id": 244,
      "label": "Division Method",
      "group": "PRACT"
    },
    {
      "id": 245,
      "label": "Spore Propagation",
      "group": "PRACT"
    },
    {
      "id": 246,
      "label": "Growth Medium Prep",
      "group": "PRACT"
    },
    {
      "id": 247,
      "label": "Moss Nursery Setup",
      "group": "PRACT"
    },
    {
      "id": 248,
      "label": "Commercial Suppliers",
      "group": "PRACT"
    },
    {
      "id": 249,
      "label": "Sustainability Certs",
      "group": "PRACT"
    },
    {
      "id": 250,
      "label": "Browning Moss Causes",
      "group": "PRACT"
    },
    {
      "id": 251,
      "label": "Drying Issues",
      "group": "PRACT"
    },
    {
      "id": 252,
      "label": "Overwatering Myths",
      "group": "PRACT"
    },
    {
      "id": 253,
      "label": "Moss Pest Control",
      "group": "PRACT"
    },
    {
      "id": 254,
      "label": "Mold Management",
      "group": "PRACT"
    },
    {
      "id": 255,
      "label": "Algae Competition",
      "group": "PRACT"
    },
    {
      "id": 256,
      "label": "Weed Removal",
      "group": "PRACT"
    },
    {
      "id": 257,
      "label": "Substrate Selection",
      "group": "PRACT"
    },
    {
      "id": 258,
      "label": "Perlite Use",
      "group": "PRACT"
    },
    {
      "id": 259,
      "label": "Peat-Free Substrates",
      "group": "PRACT"
    },
    {
      "id": 260,
      "label": "Mist Systems",
      "group": "PRACT"
    },
    {
      "id": 261,
      "label": "Spray Bottle Technique",
      "group": "PRACT"
    },
    {
      "id": 262,
      "label": "Automated Misting",
      "group": "PRACT"
    },
    {
      "id": 263,
      "label": "Lighting Options",
      "group": "PRACT"
    },
    {
      "id": 264,
      "label": "Natural vs Artificial Light",
      "group": "PRACT"
    },
    {
      "id": 265,
      "label": "Light Spectrum Needs",
      "group": "PRACT"
    },
    {
      "id": 266,
      "label": "Humidity Control",
      "group": "PRACT"
    },
    {
      "id": 267,
      "label": "Temperature Management",
      "group": "PRACT"
    },
    {
      "id": 268,
      "label": "Air Circulation",
      "group": "PRACT",
      "shape": "box"
    },
    {
      "id": 269,
      "label": "Water Quality",
      "group": "PRACT"
    },
    {
      "id": 270,
      "label": "Rainwater Collection",
      "group": "PRACT"
    },
    {
      "id": 271,
      "label": "Distilled Water Use",
      "group": "PRACT"
    },
    {
      "id": 272,
      "label": "Moss in K-12 Education",
      "group": "EDUC"
    },
    {
      "id": 273,
      "label": "Hands-On Moss Labs",
      "group": "EDUC"
    },
    {
      "id": 274,
      "label": "Outdoor Exploration",
      "group": "EDUC"
    },
    {
      "id": 275,
      "label": "Simple Experiments",
      "group": "EDUC"
    },
    {
      "id": 276,
      "label": "Moss STEM Integration",
      "group": "EDUC"
    },
    {
      "id": 277,
      "label": "Biology Lesson Plans",
      "group": "EDUC"
    },
    {
      "id": 278,
      "label": "Systems Thinking Labs",
      "group": "EDUC"
    },
    {
      "id": 279,
      "label": "Microscope Activities",
      "group": "EDUC"
    },
    {
      "id": 280,
      "label": "Moss Journaling",
      "group": "EDUC"
    },
    {
      "id": 281,
      "label": "Nature Walk Curriculum",
      "group": "EDUC"
    },
    {
      "id": 282,
      "label": "Moss in Senior Living",
      "group": "EDUC"
    },
    {
      "id": 283,
      "label": "Therapeutic Gardens",
      "group": "EDUC"
    },
    {
      "id": 284,
      "label": "Low-Maintenance Greenery",
      "group": "EDUC"
    },
    {
      "id": 285,
      "label": "Sensory Engagement",
      "group": "EDUC"
    },
    {
      "id": 286,
      "label": "Horticultural Therapy",
      "group": "EDUC"
    },
    {
      "id": 287,
      "label": "Memory Care Gardens",
      "group": "EDUC"
    },
    {
      "id": 288,
      "label": "Accessibility Design",
      "group": "EDUC"
    },
    {
      "id": 289,
      "label": "Intergenerational Projects",
      "group": "EDUC"
    },
    {
      "id": 290,
      "label": "Community Moss Gardens",
      "group": "EDUC"
    },
    {
      "id": 291,
      "label": "Citizen Science",
      "group": "EDUC"
    },
    {
      "id": 292,
      "label": "Systems Thinking",
      "group": "ADV"
    },
    {
      "id": 293,
      "label": "Distributed Systems",
      "group": "ADV"
    },
    {
      "id": 294,
      "label": "Resilience Patterns",
      "group": "ADV"
    },
    {
      "id": 295,
      "label": "Low-Resource Optimization",
      "group": "ADV"
    },
    {
      "id": 296,
      "label": "Feedback Loops",
      "group": "ADV",
      "shape": "box"
    },
    {
      "id": 297,
      "label": "Emergent Properties",
      "group": "ADV",
      "shape": "box"
    },
    {
      "id": 298,
      "label": "Biomimicry",
      "group": "ADV"
    },
    {
      "id": 299,
      "label": "Water Capture Strategies",
      "group": "ADV"
    },
    {
      "id": 300,
      "label": "Surface Optimization",
      "group": "ADV"
    },
    {
      "id": 301,
      "label": "Passive Design Lessons",
      "group": "ADV"
    },
    {
      "id": 302,
      "label": "Bio-Inspired Materials",
      "group": "ADV"
    },
    {
      "id": 303,
      "label": "Growth Rate Measurement",
      "group": "ADV"
    },
    {
      "id": 304,
      "label": "Moisture Sensors",
      "group": "ADV"
    },
    {
      "id": 305,
      "label": "Data Collection Methods",
      "group": "ADV"
    },
    {
      "id": 306,
      "label": "Experimental Design",
      "group": "ADV"
    },
    {
      "id": 307,
      "label": "Scientific Method Review",
      "group": "ADV",
      "shape": "box"
    },
    {
      "id": 308,
      "label": "Hypothesis Testing",
      "group": "ADV"
    },
    {
      "id": 309,
      "label": "Data Visualization",
      "group": "ADV"
    },
    {
      "id": 310,
      "label": "Statistical Analysis",
      "group": "ADV"
    },
    {
      "id": 311,
      "label": "Citizen Science Projects",
      "group": "ADV"
    },
    {
      "id": 312,
      "label": "iNaturalist Platform",
      "group": "ADV"
    },
    {
      "id": 313,
      "label": "Moss Surveys",
      "group": "ADV"
    },
    {
      "id": 314,
      "label": "Species Mapping",
      "group": "ADV"
    },
    {
      "id": 315,
      "label": "AI Moss Identification",
      "group": "ADV"
    },
    {
      "id": 316,
      "label": "Image Recognition",
      "group": "ADV"
    },
    {
      "id": 317,
      "label": "Machine Learning Basics",
      "group": "ADV",
      "shape": "box"
    },
    {
      "id": 318,
      "label": "Garden Recommendation AI",
      "group": "ADV"
    },
    {
      "id": 319,
      "label": "Adaptive Learning Systems",
      "group": "ADV"
    },
    {
      "id": 320,
      "label": "MicroSim Development",
      "group": "ADV"
    },
    {
      "id": 321,
      "label": "Simulation Modeling",
      "group": "ADV"
    },
    {
      "id": 322,
      "label": "Parameter Tuning",
      "group": "ADV"
    },
    {
      "id": 323,
      "label": "Interactive Visualization",
      "group": "ADV"
    },
    {
      "id": 324,
      "label": "Moss in Space Habitats",
      "group": "FUTURE"
    },
    {
      "id": 325,
      "label": "Closed-Loop Ecosystems",
      "group": "FUTURE"
    },
    {
      "id": 326,
      "label": "Life Support Systems",
      "group": "FUTURE"
    },
    {
      "id": 327,
      "label": "Low-Resource Plants",
      "group": "FUTURE"
    },
    {
      "id": 328,
      "label": "Mars Habitat Design",
      "group": "FUTURE"
    },
    {
      "id": 329,
      "label": "Synthetic Biology",
      "group": "FUTURE"
    },
    {
      "id": 330,
      "label": "Engineered Moss",
      "group": "FUTURE"
    },
    {
      "id": 331,
      "label": "Gene Editing Overview",
      "group": "FUTURE"
    },
    {
      "id": 332,
      "label": "Bioengineering Ethics",
      "group": "FUTURE"
    },
    {
      "id": 333,
      "label": "Bio-Materials",
      "group": "FUTURE"
    },
    {
      "id": 334,
      "label": "Moss-Based Insulation",
      "group": "FUTURE"
    },
    {
      "id": 335,
      "label": "Carbon-Negative Materials",
      "group": "FUTURE"
    },
    {
      "id": 336,
      "label": "Sustainable Packaging",
      "group": "FUTURE"
    },
    {
      "id": 337,
      "label": "Biodegradable Materials",
      "group": "FUTURE"
    },
    {
      "id": 338,
      "label": "Circular Economy",
      "group": "FUTURE"
    },
    {
      "id": 339,
      "label": "Green Manufacturing",
      "group": "FUTURE"
    },
    {
      "id": 340,
      "label": "Moss Biotechnology",
      "group": "FUTURE"
    },
    {
      "id": 341,
      "label": "Phytoremediation",
      "group": "FUTURE"
    },
    {
      "id": 342,
      "label": "Environmental Restoration",
      "group": "FUTURE"
    },
    {
      "id": 343,
      "label": "Rewilding with Moss",
      "group": "FUTURE"
    },
    {
      "id": 344,
      "label": "Ecosystem Engineering",
      "group": "FUTURE"
    },
    {
      "id": 345,
      "label": "Future Urban Design",
      "group": "FUTURE"
    },
    {
      "id": 346,
      "label": "Scientific Observation",
      "group": "XCUT",
      "shape": "box"
    },
    {
      "id": 347,
      "label": "Field Notebook Skills",
      "group": "XCUT"
    },
    {
      "id": 348,
      "label": "Lab Safety",
      "group": "XCUT",
      "shape": "box"
    },
    {
      "id": 349,
      "label": "Microscopy Basics",
      "group": "XCUT"
    },
    {
      "id": 350,
      "label": "Digital Documentation",
      "group": "XCUT"
    },
    {
      "id": 351,
      "label": "Research Skills",
      "group": "XCUT"
    },
    {
      "id": 352,
      "label": "Literature Review Basics",
      "group": "XCUT"
    },
    {
      "id": 353,
      "label": "Presentation Skills",
      "group": "XCUT"
    },
    {
      "id": 354,
      "label": "Technical Writing",
      "group": "XCUT",
      "shape": "box"
    },
    {
      "id": 355,
      "label": "Collaborative Learning",
      "group": "XCUT",
      "shape": "box"
    },
    {
      "id": 356,
      "label": "Project Management",
      "group": "XCUT"
    },
    {
      "id": 357,
      "label": "Design Thinking",
      "group": "XCUT",
      "shape": "box"
    },
    {
      "id": 358,
      "label": "Iterative Prototyping",
      "group": "XCUT"
    },
    {
      "id": 359,
      "label": "Evidence-Based Practice",
      "group": "XCUT"
    },
    {
      "id": 360,
      "label": "Critical Thinking",
      "group": "XCUT",
      "shape": "box"
    },
    {
      "id": 361,
      "label": "Environmental Ethics",
      "group": "XCUT"
    },
    {
      "id": 362,
      "label": "Conservation Principles",
      "group": "XCUT"
    },
    {
      "id": 363,
      "label": "Sustainability Principles",
      "group": "XCUT"
    },
    {
      "id": 364,
      "label": "Biodiversity Value",
      "group": "XCUT"
    },
    {
      "id": 365,
      "label": "Ecosystem Health",
      "group": "XCUT"
    },
    {
      "id": 366,
      "label": "Climate Literacy",
      "group": "XCUT"
    },
    {
      "id": 367,
      "label": "Water Stewardship",
      "group": "XCUT"
    },
    {
      "id": 368,
      "label": "Land Use Ethics",
      "group": "XCUT"
    },
    {
      "id": 369,
      "label": "Native Species Priority",
      "group": "XCUT"
    },
    {
      "id": 370,
      "label": "Invasive Species Aware",
      "group": "XCUT"
    },
    {
      "id": 371,
      "label": "Habitat Restoration",
      "group": "XCUT"
    },
    {
      "id": 372,
      "label": "Soil Science Basics",
      "group": "XCUT",
      "shape": "box"
    },
    {
      "id": 373,
      "label": "pH and Chemistry Basics",
      "group": "XCUT",
      "shape": "box"
    },
    {
      "id": 374,
      "label": "Light and Energy Basics",
      "group": "XCUT",
      "shape": "box"
    },
    {
      "id": 375,
      "label": "Water Cycle Basics",
      "group": "XCUT",
      "shape": "box"
    },
    {
      "id": 376,
      "label": "Nutrient Cycles",
      "group": "XCUT"
    },
    {
      "id": 377,
      "label": "Food Web Concepts",
      "group": "XCUT"
    },
    {
      "id": 378,
      "label": "Population Dynamics",
      "group": "XCUT"
    },
    {
      "id": 379,
      "label": "Community Ecology",
      "group": "XCUT"
    },
    {
      "id": 380,
      "label": "Landscape Ecology",
      "group": "XCUT"
    },
    {
      "id": 381,
      "label": "Biogeography Basics",
      "group": "XCUT"
    },
    {
      "id": 382,
      "label": "Phenology",
      "group": "XCUT"
    },
    {
      "id": 383,
      "label": "Plant Anatomy Basics",
      "group": "XCUT"
    },
    {
      "id": 384,
      "label": "Cell Biology Basics",
      "group": "XCUT",
      "shape": "box"
    },
    {
      "id": 385,
      "label": "Genetics Basics",
      "group": "XCUT"
    },
    {
      "id": 386,
      "label": "Taxonomy Basics",
      "group": "XCUT"
    },
    {
      "id": 387,
      "label": "Evolutionary Biology",
      "group": "XCUT"
    },
    {
      "id": 388,
      "label": "Adaptation",
      "group": "XCUT"
    },
    {
      "id": 389,
      "label": "Natural Selection",
      "group": "XCUT",
      "shape": "box"
    },
    {
      "id": 390,
      "label": "Convergent Evolution",
      "group": "XCUT"
    },
    {
      "id": 391,
      "label": "Coevolution",
      "group": "XCUT"
    },
    {
      "id": 392,
      "label": "Mutualism",
      "group": "XCUT"
    },
    {
      "id": 393,
      "label": "Parasitism",
      "group": "XCUT"
    },
    {
      "id": 394,
      "label": "Competition",
      "group": "XCUT"
    },
    {
      "id": 395,
      "label": "Ecological Niche",
      "group": "XCUT"
    },
    {
      "id": 396,
      "label": "Succession",
      "group": "XCUT"
    },
    {
      "id": 397,
      "label": "Disturbance Ecology",
      "group": "XCUT"
    },
    {
      "id": 398,
      "label": "Restoration Ecology",
      "group": "XCUT"
    },
    {
      "id": 399,
      "label": "Cost-Benefit Analysis",
      "group": "XCUT"
    },
    {
      "id": 400,
      "label": "Life Cycle Assessment",
      "group": "XCUT"
    }
  ],
  "edges": [
    {
      "from": 2,
      "to": 1
    },
    {
      "from": 3,
      "to": 2
    },
    {
      "from": 4,
      "to": 2
    },
    {
      "from": 5,
      "to": 1
    },
    {
      "from": 8,
      "to": 7
    },
    {
      "from": 9,
      "to": 1
    },
    {
      "from": 9,
      "to": 2
    },
    {
      "from": 10,
      "to": 9
    },
    {
      "from": 10,
      "to": 2
    },
    {
      "from": 11,
      "to": 1
    },
    {
      "from": 11,
      "to": 6
    },
    {
      "from": 12,
      "to": 1
    },
    {
      "from": 12,
      "to": 6
    },
    {
      "from": 13,
      "to": 1
    },
    {
      "from": 13,
      "to": 6
    },
    {
      "from": 14,
      "to": 1
    },
    {
      "from": 14,
      "to": 8
    },
    {
      "from": 15,
      "to": 6
    },
    {
      "from": 16,
      "to": 5
    },
    {
      "from": 16,
      "to": 15
    },
    {
      "from": 17,
      "to": 1
    },
    {
      "from": 17,
      "to": 6
    },
    {
      "from": 18,
      "to": 1
    },
    {
      "from": 18,
      "to": 7
    },
    {
      "from": 19,
      "to": 2
    },
    {
      "from": 19,
      "to": 32
    },
    {
      "from": 20,
      "to": 2
    },
    {
      "from": 20,
      "to": 32
    },
    {
      "from": 21,
      "to": 19
    },
    {
      "from": 21,
      "to": 20
    },
    {
      "from": 22,
      "to": 5
    },
    {
      "from": 22,
      "to": 19
    },
    {
      "from": 23,
      "to": 19
    },
    {
      "from": 23,
      "to": 36
    },
    {
      "from": 24,
      "to": 19
    },
    {
      "from": 24,
      "to": 36
    },
    {
      "from": 25,
      "to": 20
    },
    {
      "from": 25,
      "to": 28
    },
    {
      "from": 26,
      "to": 20
    },
    {
      "from": 26,
      "to": 25
    },
    {
      "from": 27,
      "to": 20
    },
    {
      "from": 27,
      "to": 25
    },
    {
      "from": 28,
      "to": 2
    },
    {
      "from": 29,
      "to": 28
    },
    {
      "from": 29,
      "to": 25
    },
    {
      "from": 30,
      "to": 28
    },
    {
      "from": 30,
      "to": 6
    },
    {
      "from": 31,
      "to": 19
    },
    {
      "from": 31,
      "to": 34
    },
    {
      "from": 32,
      "to": 1
    },
    {
      "from": 32,
      "to": 2
    },
    {
      "from": 33,
      "to": 28
    },
    {
      "from": 33,
      "to": 32
    },
    {
      "from": 34,
      "to": 19
    },
    {
      "from": 34,
      "to": 20
    },
    {
      "from": 35,
      "to": 1
    },
    {
      "from": 35,
      "to": 32
    },
    {
      "from": 36,
      "to": 1
    },
    {
      "from": 36,
      "to": 384
    },
    {
      "from": 37,
      "to": 36
    },
    {
      "from": 37,
      "to": 38
    },
    {
      "from": 38,
      "to": 36
    },
    {
      "from": 38,
      "to": 374
    },
    {
      "from": 39,
      "to": 1
    },
    {
      "from": 39,
      "to": 58
    },
    {
      "from": 40,
      "to": 1
    },
    {
      "from": 40,
      "to": 58
    },
    {
      "from": 41,
      "to": 1
    },
    {
      "from": 41,
      "to": 56
    },
    {
      "from": 42,
      "to": 1
    },
    {
      "from": 42,
      "to": 58
    },
    {
      "from": 43,
      "to": 1
    },
    {
      "from": 43,
      "to": 44
    },
    {
      "from": 44,
      "to": 1
    },
    {
      "from": 44,
      "to": 2
    },
    {
      "from": 45,
      "to": 1
    },
    {
      "from": 45,
      "to": 57
    },
    {
      "from": 46,
      "to": 1
    },
    {
      "from": 46,
      "to": 56
    },
    {
      "from": 47,
      "to": 1
    },
    {
      "from": 47,
      "to": 10
    },
    {
      "from": 48,
      "to": 1
    },
    {
      "from": 48,
      "to": 53
    },
    {
      "from": 49,
      "to": 1
    },
    {
      "from": 49,
      "to": 56
    },
    {
      "from": 50,
      "to": 1
    },
    {
      "from": 50,
      "to": 56
    },
    {
      "from": 51,
      "to": 1
    },
    {
      "from": 51,
      "to": 57
    },
    {
      "from": 52,
      "to": 1
    },
    {
      "from": 52,
      "to": 55
    },
    {
      "from": 53,
      "to": 1
    },
    {
      "from": 53,
      "to": 55
    },
    {
      "from": 54,
      "to": 1
    },
    {
      "from": 54,
      "to": 55
    },
    {
      "from": 54,
      "to": 97
    },
    {
      "from": 55,
      "to": 1
    },
    {
      "from": 55,
      "to": 66
    },
    {
      "from": 56,
      "to": 1
    },
    {
      "from": 56,
      "to": 58
    },
    {
      "from": 57,
      "to": 1
    },
    {
      "from": 57,
      "to": 58
    },
    {
      "from": 58,
      "to": 1
    },
    {
      "from": 58,
      "to": 9
    },
    {
      "from": 59,
      "to": 10
    },
    {
      "from": 59,
      "to": 63
    },
    {
      "from": 59,
      "to": 64
    },
    {
      "from": 59,
      "to": 65
    },
    {
      "from": 60,
      "to": 59
    },
    {
      "from": 60,
      "to": 62
    },
    {
      "from": 61,
      "to": 59
    },
    {
      "from": 61,
      "to": 386
    },
    {
      "from": 62,
      "to": 59
    },
    {
      "from": 62,
      "to": 350
    },
    {
      "from": 63,
      "to": 1
    },
    {
      "from": 63,
      "to": 346
    },
    {
      "from": 64,
      "to": 1
    },
    {
      "from": 64,
      "to": 36
    },
    {
      "from": 65,
      "to": 1
    },
    {
      "from": 65,
      "to": 58
    },
    {
      "from": 66,
      "to": 1
    },
    {
      "from": 66,
      "to": 67
    },
    {
      "from": 68,
      "to": 1
    },
    {
      "from": 68,
      "to": 77
    },
    {
      "from": 68,
      "to": 78
    },
    {
      "from": 69,
      "to": 1
    },
    {
      "from": 69,
      "to": 372
    },
    {
      "from": 70,
      "to": 66
    },
    {
      "from": 71,
      "to": 66
    },
    {
      "from": 72,
      "to": 52
    },
    {
      "from": 72,
      "to": 66
    },
    {
      "from": 73,
      "to": 66
    },
    {
      "from": 73,
      "to": 84
    },
    {
      "from": 74,
      "to": 66
    },
    {
      "from": 74,
      "to": 108
    },
    {
      "from": 75,
      "to": 66
    },
    {
      "from": 75,
      "to": 84
    },
    {
      "from": 76,
      "to": 9
    },
    {
      "from": 76,
      "to": 66
    },
    {
      "from": 76,
      "to": 364
    },
    {
      "from": 77,
      "to": 16
    },
    {
      "from": 77,
      "to": 375
    },
    {
      "from": 78,
      "to": 16
    },
    {
      "from": 78,
      "to": 77
    },
    {
      "from": 79,
      "to": 78
    },
    {
      "from": 80,
      "to": 68
    },
    {
      "from": 80,
      "to": 82
    },
    {
      "from": 81,
      "to": 68
    },
    {
      "from": 81,
      "to": 82
    },
    {
      "from": 82,
      "to": 375
    },
    {
      "from": 83,
      "to": 68
    },
    {
      "from": 83,
      "to": 110
    },
    {
      "from": 84,
      "to": 18
    },
    {
      "from": 84,
      "to": 68
    },
    {
      "from": 85,
      "to": 84
    },
    {
      "from": 86,
      "to": 38
    },
    {
      "from": 86,
      "to": 87
    },
    {
      "from": 88,
      "to": 86
    },
    {
      "from": 88,
      "to": 87
    },
    {
      "from": 89,
      "to": 87
    },
    {
      "from": 90,
      "to": 89
    },
    {
      "from": 90,
      "to": 94
    },
    {
      "from": 91,
      "to": 89
    },
    {
      "from": 91,
      "to": 18
    },
    {
      "from": 92,
      "to": 66
    },
    {
      "from": 93,
      "to": 92
    },
    {
      "from": 93,
      "to": 98
    },
    {
      "from": 94,
      "to": 66
    },
    {
      "from": 94,
      "to": 92
    },
    {
      "from": 95,
      "to": 92
    },
    {
      "from": 95,
      "to": 78
    },
    {
      "from": 96,
      "to": 92
    },
    {
      "from": 96,
      "to": 373
    },
    {
      "from": 97,
      "to": 66
    },
    {
      "from": 97,
      "to": 379
    },
    {
      "from": 98,
      "to": 66
    },
    {
      "from": 98,
      "to": 305
    },
    {
      "from": 99,
      "to": 66
    },
    {
      "from": 100,
      "to": 99
    },
    {
      "from": 101,
      "to": 99
    },
    {
      "from": 102,
      "to": 100
    },
    {
      "from": 102,
      "to": 376
    },
    {
      "from": 103,
      "to": 66
    },
    {
      "from": 104,
      "to": 66
    },
    {
      "from": 104,
      "to": 376
    },
    {
      "from": 105,
      "to": 376
    },
    {
      "from": 105,
      "to": 104
    },
    {
      "from": 106,
      "to": 66
    },
    {
      "from": 106,
      "to": 377
    },
    {
      "from": 107,
      "to": 66
    },
    {
      "from": 107,
      "to": 71
    },
    {
      "from": 108,
      "to": 44
    },
    {
      "from": 108,
      "to": 109
    },
    {
      "from": 109,
      "to": 44
    },
    {
      "from": 109,
      "to": 66
    },
    {
      "from": 110,
      "to": 43
    },
    {
      "from": 110,
      "to": 68
    },
    {
      "from": 111,
      "to": 74
    },
    {
      "from": 111,
      "to": 362
    },
    {
      "from": 112,
      "to": 1
    },
    {
      "from": 112,
      "to": 113
    },
    {
      "from": 112,
      "to": 116
    },
    {
      "from": 113,
      "to": 1
    },
    {
      "from": 113,
      "to": 67
    },
    {
      "from": 114,
      "to": 112
    },
    {
      "from": 114,
      "to": 140
    },
    {
      "from": 115,
      "to": 1
    },
    {
      "from": 115,
      "to": 118
    },
    {
      "from": 116,
      "to": 1
    },
    {
      "from": 116,
      "to": 64
    },
    {
      "from": 116,
      "to": 65
    },
    {
      "from": 117,
      "to": 118
    },
    {
      "from": 117,
      "to": 119
    },
    {
      "from": 117,
      "to": 120
    },
    {
      "from": 117,
      "to": 122
    },
    {
      "from": 118,
      "to": 374
    },
    {
      "from": 119,
      "to": 375
    },
    {
      "from": 120,
      "to": 372
    },
    {
      "from": 120,
      "to": 373
    },
    {
      "from": 121,
      "to": 120
    },
    {
      "from": 121,
      "to": 306
    },
    {
      "from": 123,
      "to": 122
    },
    {
      "from": 124,
      "to": 117
    },
    {
      "from": 124,
      "to": 59
    },
    {
      "from": 125,
      "to": 117
    },
    {
      "from": 125,
      "to": 127
    },
    {
      "from": 126,
      "to": 125
    },
    {
      "from": 127,
      "to": 372
    },
    {
      "from": 128,
      "to": 124
    },
    {
      "from": 128,
      "to": 125
    },
    {
      "from": 128,
      "to": 236
    },
    {
      "from": 129,
      "to": 128
    },
    {
      "from": 129,
      "to": 130
    },
    {
      "from": 130,
      "to": 119
    },
    {
      "from": 130,
      "to": 269
    },
    {
      "from": 131,
      "to": 224
    },
    {
      "from": 131,
      "to": 112
    },
    {
      "from": 132,
      "to": 112
    },
    {
      "from": 132,
      "to": 138
    },
    {
      "from": 133,
      "to": 226
    },
    {
      "from": 133,
      "to": 112
    },
    {
      "from": 134,
      "to": 112
    },
    {
      "from": 134,
      "to": 135
    },
    {
      "from": 135,
      "to": 112
    },
    {
      "from": 135,
      "to": 116
    },
    {
      "from": 136,
      "to": 112
    },
    {
      "from": 136,
      "to": 124
    },
    {
      "from": 137,
      "to": 124
    },
    {
      "from": 137,
      "to": 138
    },
    {
      "from": 138,
      "to": 112
    },
    {
      "from": 138,
      "to": 115
    },
    {
      "from": 138,
      "to": 118
    },
    {
      "from": 139,
      "to": 112
    },
    {
      "from": 139,
      "to": 196
    },
    {
      "from": 140,
      "to": 112
    },
    {
      "from": 140,
      "to": 141
    },
    {
      "from": 141,
      "to": 112
    },
    {
      "from": 141,
      "to": 6
    },
    {
      "from": 142,
      "to": 140
    },
    {
      "from": 142,
      "to": 399
    },
    {
      "from": 143,
      "to": 140
    },
    {
      "from": 143,
      "to": 367
    },
    {
      "from": 144,
      "to": 140
    },
    {
      "from": 144,
      "to": 361
    },
    {
      "from": 145,
      "to": 140
    },
    {
      "from": 145,
      "to": 86
    },
    {
      "from": 145,
      "to": 400
    },
    {
      "from": 146,
      "to": 129
    },
    {
      "from": 146,
      "to": 382
    },
    {
      "from": 147,
      "to": 129
    },
    {
      "from": 147,
      "to": 148
    },
    {
      "from": 147,
      "to": 149
    },
    {
      "from": 148,
      "to": 1
    },
    {
      "from": 148,
      "to": 84
    },
    {
      "from": 149,
      "to": 148
    },
    {
      "from": 149,
      "to": 85
    },
    {
      "from": 150,
      "to": 1
    },
    {
      "from": 150,
      "to": 112
    },
    {
      "from": 151,
      "to": 150
    },
    {
      "from": 151,
      "to": 160
    },
    {
      "from": 152,
      "to": 150
    },
    {
      "from": 152,
      "to": 160
    },
    {
      "from": 153,
      "to": 150
    },
    {
      "from": 153,
      "to": 154
    },
    {
      "from": 154,
      "to": 150
    },
    {
      "from": 155,
      "to": 150
    },
    {
      "from": 155,
      "to": 257
    },
    {
      "from": 156,
      "to": 155
    },
    {
      "from": 157,
      "to": 155
    },
    {
      "from": 158,
      "to": 155
    },
    {
      "from": 158,
      "to": 372
    },
    {
      "from": 159,
      "to": 153
    },
    {
      "from": 159,
      "to": 155
    },
    {
      "from": 159,
      "to": 156
    },
    {
      "from": 159,
      "to": 157
    },
    {
      "from": 159,
      "to": 158
    },
    {
      "from": 160,
      "to": 150
    },
    {
      "from": 160,
      "to": 266
    },
    {
      "from": 161,
      "to": 152
    },
    {
      "from": 161,
      "to": 160
    },
    {
      "from": 162,
      "to": 150
    },
    {
      "from": 162,
      "to": 263
    },
    {
      "from": 163,
      "to": 162
    },
    {
      "from": 163,
      "to": 265
    },
    {
      "from": 164,
      "to": 162
    },
    {
      "from": 164,
      "to": 118
    },
    {
      "from": 165,
      "to": 159
    },
    {
      "from": 165,
      "to": 166
    },
    {
      "from": 166,
      "to": 130
    },
    {
      "from": 167,
      "to": 159
    },
    {
      "from": 168,
      "to": 254
    },
    {
      "from": 169,
      "to": 253
    },
    {
      "from": 170,
      "to": 150
    },
    {
      "from": 170,
      "to": 172
    },
    {
      "from": 171,
      "to": 150
    },
    {
      "from": 171,
      "to": 154
    },
    {
      "from": 172,
      "to": 150
    },
    {
      "from": 172,
      "to": 357
    },
    {
      "from": 173,
      "to": 178
    },
    {
      "from": 173,
      "to": 176
    },
    {
      "from": 174,
      "to": 1
    },
    {
      "from": 175,
      "to": 174
    },
    {
      "from": 175,
      "to": 173
    },
    {
      "from": 176,
      "to": 178
    },
    {
      "from": 176,
      "to": 262
    },
    {
      "from": 177,
      "to": 173
    },
    {
      "from": 177,
      "to": 190
    },
    {
      "from": 178,
      "to": 150
    },
    {
      "from": 178,
      "to": 210
    },
    {
      "from": 179,
      "to": 183
    },
    {
      "from": 179,
      "to": 200
    },
    {
      "from": 180,
      "to": 179
    },
    {
      "from": 180,
      "to": 182
    },
    {
      "from": 181,
      "to": 179
    },
    {
      "from": 182,
      "to": 179
    },
    {
      "from": 182,
      "to": 183
    },
    {
      "from": 183,
      "to": 150
    },
    {
      "from": 184,
      "to": 179
    },
    {
      "from": 184,
      "to": 201
    },
    {
      "from": 185,
      "to": 210
    },
    {
      "from": 186,
      "to": 185
    },
    {
      "from": 187,
      "to": 186
    },
    {
      "from": 188,
      "to": 186
    },
    {
      "from": 189,
      "to": 1
    },
    {
      "from": 189,
      "to": 194
    },
    {
      "from": 189,
      "to": 196
    },
    {
      "from": 190,
      "to": 185
    },
    {
      "from": 190,
      "to": 213
    },
    {
      "from": 191,
      "to": 185
    },
    {
      "from": 191,
      "to": 213
    },
    {
      "from": 192,
      "to": 195
    },
    {
      "from": 193,
      "to": 68
    },
    {
      "from": 193,
      "to": 213
    },
    {
      "from": 194,
      "to": 213
    },
    {
      "from": 195,
      "to": 213
    },
    {
      "from": 196,
      "to": 68
    },
    {
      "from": 196,
      "to": 82
    },
    {
      "from": 196,
      "to": 210
    },
    {
      "from": 197,
      "to": 196
    },
    {
      "from": 197,
      "to": 209
    },
    {
      "from": 198,
      "to": 97
    },
    {
      "from": 198,
      "to": 366
    },
    {
      "from": 199,
      "to": 198
    },
    {
      "from": 199,
      "to": 185
    },
    {
      "from": 199,
      "to": 200
    },
    {
      "from": 200,
      "to": 97
    },
    {
      "from": 200,
      "to": 210
    },
    {
      "from": 201,
      "to": 179
    },
    {
      "from": 201,
      "to": 203
    },
    {
      "from": 202,
      "to": 201
    },
    {
      "from": 202,
      "to": 179
    },
    {
      "from": 203,
      "to": 399
    },
    {
      "from": 204,
      "to": 185
    },
    {
      "from": 204,
      "to": 211
    },
    {
      "from": 204,
      "to": 363
    },
    {
      "from": 205,
      "to": 204
    },
    {
      "from": 206,
      "to": 204
    },
    {
      "from": 207,
      "to": 199
    },
    {
      "from": 207,
      "to": 196
    },
    {
      "from": 207,
      "to": 204
    },
    {
      "from": 208,
      "to": 200
    },
    {
      "from": 208,
      "to": 364
    },
    {
      "from": 209,
      "to": 196
    },
    {
      "from": 209,
      "to": 210
    },
    {
      "from": 210,
      "to": 67
    },
    {
      "from": 210,
      "to": 97
    },
    {
      "from": 211,
      "to": 193
    },
    {
      "from": 211,
      "to": 194
    },
    {
      "from": 211,
      "to": 363
    },
    {
      "from": 212,
      "to": 192
    },
    {
      "from": 212,
      "to": 195
    },
    {
      "from": 214,
      "to": 1
    },
    {
      "from": 214,
      "to": 116
    },
    {
      "from": 215,
      "to": 214
    },
    {
      "from": 215,
      "to": 174
    },
    {
      "from": 216,
      "to": 214
    },
    {
      "from": 216,
      "to": 221
    },
    {
      "from": 217,
      "to": 214
    },
    {
      "from": 217,
      "to": 240
    },
    {
      "from": 218,
      "to": 214
    },
    {
      "from": 218,
      "to": 219
    },
    {
      "from": 219,
      "to": 214
    },
    {
      "from": 219,
      "to": 220
    },
    {
      "from": 220,
      "to": 214
    },
    {
      "from": 220,
      "to": 257
    },
    {
      "from": 221,
      "to": 64
    },
    {
      "from": 221,
      "to": 214
    },
    {
      "from": 222,
      "to": 65
    },
    {
      "from": 222,
      "to": 214
    },
    {
      "from": 223,
      "to": 62
    },
    {
      "from": 223,
      "to": 214
    },
    {
      "from": 224,
      "to": 225
    },
    {
      "from": 224,
      "to": 226
    },
    {
      "from": 225,
      "to": 228
    },
    {
      "from": 226,
      "to": 225
    },
    {
      "from": 227,
      "to": 224
    },
    {
      "from": 227,
      "to": 1
    },
    {
      "from": 228,
      "to": 1
    },
    {
      "from": 228,
      "to": 7
    },
    {
      "from": 229,
      "to": 228
    },
    {
      "from": 230,
      "to": 228
    },
    {
      "from": 231,
      "to": 228
    },
    {
      "from": 232,
      "to": 224
    },
    {
      "from": 232,
      "to": 234
    },
    {
      "from": 233,
      "to": 228
    },
    {
      "from": 233,
      "to": 232
    },
    {
      "from": 234,
      "to": 179
    },
    {
      "from": 234,
      "to": 283
    },
    {
      "from": 235,
      "to": 234
    },
    {
      "from": 235,
      "to": 285
    },
    {
      "from": 236,
      "to": 1
    },
    {
      "from": 236,
      "to": 237
    },
    {
      "from": 236,
      "to": 362
    },
    {
      "from": 237,
      "to": 1
    },
    {
      "from": 237,
      "to": 362
    },
    {
      "from": 238,
      "to": 237
    },
    {
      "from": 238,
      "to": 368
    },
    {
      "from": 239,
      "to": 236
    },
    {
      "from": 239,
      "to": 249
    },
    {
      "from": 240,
      "to": 1
    },
    {
      "from": 240,
      "to": 35
    },
    {
      "from": 241,
      "to": 240
    },
    {
      "from": 242,
      "to": 240
    },
    {
      "from": 243,
      "to": 242
    },
    {
      "from": 243,
      "to": 359
    },
    {
      "from": 244,
      "to": 240
    },
    {
      "from": 245,
      "to": 240
    },
    {
      "from": 245,
      "to": 28
    },
    {
      "from": 246,
      "to": 240
    },
    {
      "from": 246,
      "to": 257
    },
    {
      "from": 247,
      "to": 240
    },
    {
      "from": 247,
      "to": 246
    },
    {
      "from": 247,
      "to": 248
    },
    {
      "from": 248,
      "to": 240
    },
    {
      "from": 248,
      "to": 249
    },
    {
      "from": 249,
      "to": 363
    },
    {
      "from": 250,
      "to": 1
    },
    {
      "from": 250,
      "to": 251
    },
    {
      "from": 250,
      "to": 252
    },
    {
      "from": 251,
      "to": 1
    },
    {
      "from": 251,
      "to": 84
    },
    {
      "from": 252,
      "to": 1
    },
    {
      "from": 252,
      "to": 359
    },
    {
      "from": 253,
      "to": 1
    },
    {
      "from": 254,
      "to": 1
    },
    {
      "from": 255,
      "to": 1
    },
    {
      "from": 255,
      "to": 14
    },
    {
      "from": 255,
      "to": 394
    },
    {
      "from": 256,
      "to": 1
    },
    {
      "from": 256,
      "to": 394
    },
    {
      "from": 257,
      "to": 372
    },
    {
      "from": 258,
      "to": 257
    },
    {
      "from": 259,
      "to": 257
    },
    {
      "from": 259,
      "to": 363
    },
    {
      "from": 260,
      "to": 130
    },
    {
      "from": 261,
      "to": 130
    },
    {
      "from": 262,
      "to": 260
    },
    {
      "from": 263,
      "to": 118
    },
    {
      "from": 263,
      "to": 374
    },
    {
      "from": 264,
      "to": 263
    },
    {
      "from": 265,
      "to": 263
    },
    {
      "from": 265,
      "to": 374
    },
    {
      "from": 266,
      "to": 119
    },
    {
      "from": 266,
      "to": 268
    },
    {
      "from": 267,
      "to": 122
    },
    {
      "from": 267,
      "to": 268
    },
    {
      "from": 269,
      "to": 375
    },
    {
      "from": 270,
      "to": 269
    },
    {
      "from": 270,
      "to": 367
    },
    {
      "from": 271,
      "to": 269
    },
    {
      "from": 272,
      "to": 1
    },
    {
      "from": 272,
      "to": 276
    },
    {
      "from": 273,
      "to": 272
    },
    {
      "from": 273,
      "to": 348
    },
    {
      "from": 274,
      "to": 272
    },
    {
      "from": 275,
      "to": 272
    },
    {
      "from": 275,
      "to": 307
    },
    {
      "from": 276,
      "to": 1
    },
    {
      "from": 276,
      "to": 292
    },
    {
      "from": 277,
      "to": 272
    },
    {
      "from": 277,
      "to": 276
    },
    {
      "from": 278,
      "to": 272
    },
    {
      "from": 278,
      "to": 292
    },
    {
      "from": 279,
      "to": 272
    },
    {
      "from": 279,
      "to": 349
    },
    {
      "from": 280,
      "to": 272
    },
    {
      "from": 280,
      "to": 347
    },
    {
      "from": 281,
      "to": 272
    },
    {
      "from": 281,
      "to": 274
    },
    {
      "from": 282,
      "to": 1
    },
    {
      "from": 283,
      "to": 112
    },
    {
      "from": 283,
      "to": 286
    },
    {
      "from": 284,
      "to": 112
    },
    {
      "from": 284,
      "to": 113
    },
    {
      "from": 285,
      "to": 283
    },
    {
      "from": 286,
      "to": 112
    },
    {
      "from": 287,
      "to": 282
    },
    {
      "from": 287,
      "to": 286
    },
    {
      "from": 288,
      "to": 282
    },
    {
      "from": 288,
      "to": 357
    },
    {
      "from": 289,
      "to": 272
    },
    {
      "from": 289,
      "to": 282
    },
    {
      "from": 289,
      "to": 355
    },
    {
      "from": 290,
      "to": 112
    },
    {
      "from": 290,
      "to": 289
    },
    {
      "from": 290,
      "to": 355
    },
    {
      "from": 291,
      "to": 311
    },
    {
      "from": 292,
      "to": 296
    },
    {
      "from": 292,
      "to": 297
    },
    {
      "from": 293,
      "to": 292
    },
    {
      "from": 293,
      "to": 16
    },
    {
      "from": 294,
      "to": 292
    },
    {
      "from": 294,
      "to": 18
    },
    {
      "from": 295,
      "to": 292
    },
    {
      "from": 295,
      "to": 16
    },
    {
      "from": 298,
      "to": 292
    },
    {
      "from": 299,
      "to": 78
    },
    {
      "from": 299,
      "to": 79
    },
    {
      "from": 300,
      "to": 298
    },
    {
      "from": 301,
      "to": 298
    },
    {
      "from": 301,
      "to": 192
    },
    {
      "from": 302,
      "to": 298
    },
    {
      "from": 302,
      "to": 333
    },
    {
      "from": 303,
      "to": 305
    },
    {
      "from": 303,
      "to": 17
    },
    {
      "from": 304,
      "to": 305
    },
    {
      "from": 304,
      "to": 119
    },
    {
      "from": 305,
      "to": 307
    },
    {
      "from": 306,
      "to": 307
    },
    {
      "from": 306,
      "to": 308
    },
    {
      "from": 308,
      "to": 307
    },
    {
      "from": 309,
      "to": 305
    },
    {
      "from": 310,
      "to": 305
    },
    {
      "from": 310,
      "to": 308
    },
    {
      "from": 311,
      "to": 305
    },
    {
      "from": 311,
      "to": 312
    },
    {
      "from": 312,
      "to": 305
    },
    {
      "from": 312,
      "to": 350
    },
    {
      "from": 313,
      "to": 311
    },
    {
      "from": 313,
      "to": 314
    },
    {
      "from": 314,
      "to": 311
    },
    {
      "from": 314,
      "to": 59
    },
    {
      "from": 315,
      "to": 316
    },
    {
      "from": 315,
      "to": 59
    },
    {
      "from": 316,
      "to": 317
    },
    {
      "from": 318,
      "to": 315
    },
    {
      "from": 318,
      "to": 124
    },
    {
      "from": 318,
      "to": 317
    },
    {
      "from": 319,
      "to": 317
    },
    {
      "from": 319,
      "to": 318
    },
    {
      "from": 320,
      "to": 321
    },
    {
      "from": 320,
      "to": 323
    },
    {
      "from": 321,
      "to": 310
    },
    {
      "from": 322,
      "to": 320
    },
    {
      "from": 322,
      "to": 321
    },
    {
      "from": 323,
      "to": 309
    },
    {
      "from": 324,
      "to": 325
    },
    {
      "from": 324,
      "to": 327
    },
    {
      "from": 325,
      "to": 292
    },
    {
      "from": 326,
      "to": 325
    },
    {
      "from": 327,
      "to": 5
    },
    {
      "from": 327,
      "to": 295
    },
    {
      "from": 328,
      "to": 324
    },
    {
      "from": 328,
      "to": 325
    },
    {
      "from": 329,
      "to": 385
    },
    {
      "from": 330,
      "to": 329
    },
    {
      "from": 330,
      "to": 340
    },
    {
      "from": 331,
      "to": 329
    },
    {
      "from": 331,
      "to": 385
    },
    {
      "from": 332,
      "to": 329
    },
    {
      "from": 332,
      "to": 361
    },
    {
      "from": 333,
      "to": 340
    },
    {
      "from": 334,
      "to": 333
    },
    {
      "from": 334,
      "to": 195
    },
    {
      "from": 335,
      "to": 333
    },
    {
      "from": 335,
      "to": 86
    },
    {
      "from": 336,
      "to": 333
    },
    {
      "from": 336,
      "to": 337
    },
    {
      "from": 337,
      "to": 333
    },
    {
      "from": 338,
      "to": 363
    },
    {
      "from": 339,
      "to": 338
    },
    {
      "from": 339,
      "to": 363
    },
    {
      "from": 340,
      "to": 1
    },
    {
      "from": 341,
      "to": 95
    },
    {
      "from": 341,
      "to": 342
    },
    {
      "from": 342,
      "to": 371
    },
    {
      "from": 343,
      "to": 342
    },
    {
      "from": 343,
      "to": 369
    },
    {
      "from": 344,
      "to": 342
    },
    {
      "from": 344,
      "to": 292
    },
    {
      "from": 345,
      "to": 207
    },
    {
      "from": 345,
      "to": 204
    },
    {
      "from": 347,
      "to": 346
    },
    {
      "from": 349,
      "to": 346
    },
    {
      "from": 350,
      "to": 346
    },
    {
      "from": 351,
      "to": 352
    },
    {
      "from": 351,
      "to": 354
    },
    {
      "from": 352,
      "to": 360
    },
    {
      "from": 353,
      "to": 354
    },
    {
      "from": 356,
      "to": 357
    },
    {
      "from": 358,
      "to": 357
    },
    {
      "from": 359,
      "to": 307
    },
    {
      "from": 359,
      "to": 360
    },
    {
      "from": 361,
      "to": 360
    },
    {
      "from": 362,
      "to": 361
    },
    {
      "from": 363,
      "to": 361
    },
    {
      "from": 364,
      "to": 362
    },
    {
      "from": 364,
      "to": 66
    },
    {
      "from": 365,
      "to": 66
    },
    {
      "from": 365,
      "to": 364
    },
    {
      "from": 366,
      "to": 87
    },
    {
      "from": 366,
      "to": 89
    },
    {
      "from": 367,
      "to": 375
    },
    {
      "from": 367,
      "to": 361
    },
    {
      "from": 368,
      "to": 361
    },
    {
      "from": 369,
      "to": 362
    },
    {
      "from": 369,
      "to": 66
    },
    {
      "from": 370,
      "to": 362
    },
    {
      "from": 370,
      "to": 66
    },
    {
      "from": 371,
      "to": 362
    },
    {
      "from": 376,
      "to": 87
    },
    {
      "from": 376,
      "to": 375
    },
    {
      "from": 377,
      "to": 376
    },
    {
      "from": 378,
      "to": 379
    },
    {
      "from": 379,
      "to": 66
    },
    {
      "from": 380,
      "to": 379
    },
    {
      "from": 380,
      "to": 381
    },
    {
      "from": 381,
      "to": 7
    },
    {
      "from": 382,
      "to": 66
    },
    {
      "from": 382,
      "to": 122
    },
    {
      "from": 383,
      "to": 6
    },
    {
      "from": 385,
      "to": 384
    },
    {
      "from": 386,
      "to": 10
    },
    {
      "from": 387,
      "to": 7
    },
    {
      "from": 387,
      "to": 389
    },
    {
      "from": 388,
      "to": 387
    },
    {
      "from": 390,
      "to": 387
    },
    {
      "from": 390,
      "to": 388
    },
    {
      "from": 391,
      "to": 387
    },
    {
      "from": 392,
      "to": 103
    },
    {
      "from": 393,
      "to": 66
    },
    {
      "from": 394,
      "to": 379
    },
    {
      "from": 395,
      "to": 379
    },
    {
      "from": 395,
      "to": 394
    },
    {
      "from": 396,
      "to": 66
    },
    {
      "from": 396,
      "to": 70
    },
    {
      "from": 397,
      "to": 396
    },
    {
      "from": 398,
      "to": 362
    },
    {
      "from": 399,
      "to": 360
    },
    {
      "from": 400,
      "to": 363
    },
    {
      "from": 400,
      "to": 399
    }
  ]
}